meta_test_family-0.8.5.dist-info/METADATA
meta_test_family-0.8.5.dist-info/RECORD
meta_test_family-0.8.5.dist-info/WHEEL
meta_test_family-0.8.5.dist-info/entry_points.txt
meta_test_family-0.8.5.dist-info/top_level.txt
meta_test_family-0.8.5.dist-info/zip-safe
moduleframework/__init__.py
moduleframework/__init__.pyc
moduleframework/bashhelper.py
moduleframework/common.py
moduleframework/compose_info.py
moduleframework/core.py
moduleframework/core.pyc
moduleframework/dockerlinter.py
moduleframework/helpfile_linter.py
moduleframework/module_framework.py
moduleframework/mtf_environment.py
moduleframework/mtf_generator.py
moduleframework/mtf_init.py
moduleframework/mtf_scheduler.py
moduleframework/mtfexceptions.py
moduleframework/pdc_data.py
moduleframework/pdc_msg_module_info_reader.py
moduleframework/timeoutlib.py
moduleframework/avocado_testers/__init__.py
moduleframework/avocado_testers/avocado_test.py
moduleframework/avocado_testers/container_avocado_test.py
moduleframework/avocado_testers/nspawn_avocado_test.py
moduleframework/avocado_testers/openshift_avocado_test.py
moduleframework/avocado_testers/rpm_avocado_test.py
moduleframework/environment_prepare/__init__.py
moduleframework/environment_prepare/docker_prepare.py
moduleframework/environment_prepare/nspawn_prepare.py
moduleframework/environment_prepare/openshift_prepare.py
moduleframework/environment_prepare/rpm_prepare.py
moduleframework/helpers/__init__.py
moduleframework/helpers/container_helper.py
moduleframework/helpers/nspawn_helper.py
moduleframework/helpers/openshift_helper.py
moduleframework/helpers/rpm_helper.py
moduleframework/tests/__init__.py
moduleframework/tests/generic/check_compose.py
moduleframework/tests/generic/dockerlint.py
moduleframework/tests/generic/main.fmf
moduleframework/tests/generic/modulelint.py
moduleframework/tests/generic/rpmvalidation.py
moduleframework/tests/static/dockerfile_lint.py
moduleframework/tests/static/helpmd_lint.py
moduleframework/tests/static/main.fmf
mtf/__init__.py
mtf/backend/__init__.py
mtf/backend/nspawn.py
mtf/common/__init__.py
mtf/metadata/__init__.py
mtf/metadata/setup.py
mtf/metadata/tmet/__init__.py
mtf/metadata/tmet/agregator.py
