Metadata-Version: 2.1
Name: meta-test-family
Version: 0.8.5
Summary: Tool to test components for a modular Fedora.
Home-page: https://github.com/fedora-modularity/meta-test-family
Author: Jan Scotka
Author-email: jscotka@redhat.com
License: GPLv2+
Keywords: modules,containers,testing,framework
Platform: UNKNOWN
Classifier: Development Status :: 4 - Beta
Classifier: Environment :: Console
Classifier: Intended Audience :: Developers
Classifier: License :: OSI Approved :: GNU General Public License v2 or later (GPLv2+)
Classifier: Operating System :: POSIX :: Linux
Classifier: Programming Language :: Python
Classifier: Topic :: Software Development
Requires-Dist: PyYAML
Requires-Dist: avocado-framework
Requires-Dist: dockerfile-parse
Requires-Dist: modulemd
Requires-Dist: netifaces
Requires-Dist: pdc-client
Requires-Dist: pexpect
Requires-Dist: pytest
